{
  "on": true,
  "tt": 60000,
  "bri": 255,
  "ledmap": 0,
  "mainseg": 0,
  "seg": [
    {
      "id": 0,
      "start": 0,
      "stop": 20,
      "on": true,
      "col": [[255, 0, 0]]
    },
    {
      "id": 1,
      "start": 20,
      "stop": 40,
      "on": true,
      "col": [[255, 0, 0]]
    },
    {
      "id": 2,
      "start": 40,
      "stop": 60,
      "on": true,
      "col": [[255, 0, 0]]
    },
    {
      "id": 3,
      "start": 60,
      "stop": 80,
      "on": true,
      "col": [[255, 0, 0]]
    },
    {
      "id": 4,
      "start": 80,
      "stop": 100,
      "on": true,
      "col": [[255, 0, 0]]
    }
  ]
}
